judo/__init__.py
judo/cli.py
judo/assets/__init__.py
judo/assets/logos/__init__.py
judo/assets/logos/logo_centyc.png
judo/assets/logos/logo_judo.png
judo/behave/__init__.py
judo/behave/auto_hooks.py
judo/behave/context.py
judo/behave/formatter.py
judo/behave/hooks.py
judo/behave/step_wrapper.py
judo/behave/steps.py
judo/behave/steps_es.py
judo/core/__init__.py
judo/core/judo.py
judo/core/judo_extended.py
judo/core/matcher.py
judo/core/response.py
judo/core/variables.py
judo/features/__init__.py
judo/features/assertions.py
judo/features/auth.py
judo/features/caching.py
judo/features/chaos.py
judo/features/contract.py
judo/features/data_driven.py
judo/features/graphql.py
judo/features/interceptors.py
judo/features/logging.py
judo/features/performance.py
judo/features/rate_limiter.py
judo/features/reporting.py
judo/features/retry.py
judo/features/websocket.py
judo/http/__init__.py
judo/http/client.py
judo/mock/__init__.py
judo/mock/server.py
judo/reporting/__init__.py
judo/reporting/html_reporter.py
judo/reporting/report_data.py
judo/reporting/reporter.py
judo/runner/__init__.py
judo/runner/base_runner.py
judo/runner/judo_runner.py
judo/runner/parallel_runner.py
judo/runner/test_suite.py
judo/utils/__init__.py
judo/utils/file_loader.py
judo/utils/helpers.py
judo/utils/safe_print.py
judo_framework-1.5.9.5.dist-info/licenses/LICENSE
judo_framework-1.5.9.5.dist-info/METADATA
judo_framework-1.5.9.5.dist-info/WHEEL
judo_framework-1.5.9.5.dist-info/entry_points.txt
judo_framework-1.5.9.5.dist-info/top_level.txt
judo_framework-1.5.9.5.dist-info/RECORD
