Metadata-Version: 2.4
Name: judo-framework
Version: 1.5.9.5
Summary: A comprehensive API testing framework for Python, inspired by Karate Framework
Home-page: https://github.com/FelipeFariasAlfaro/Judo-Framework
Author: Felipe Farias - CENTYC
Author-email: Felipe Farias - CENTYC <felipe.farias@centyc.cl>
License: MIT License
Project-URL: Homepage, https://github.com/FelipeFariasAlfaro/Judo-Framework
Project-URL: Documentation, http://centyc.cl/judo-framework/
Project-URL: Repository, https://github.com/FelipeFariasAlfaro/Judo-Framework
Project-URL: Issues, https://github.com/FelipeFariasAlfaro/Judo-Framework/issues
Project-URL: CENTYC, https://www.centyc.cl
Project-URL: Official Docs, http://centyc.cl/judo-framework/
Classifier: Development Status :: 5 - Production/Stable
Classifier: Intended Audience :: Developers
Classifier: License :: OSI Approved :: MIT License
Classifier: Operating System :: OS Independent
Classifier: Programming Language :: Python :: 3
Classifier: Programming Language :: Python :: 3.8
Classifier: Programming Language :: Python :: 3.9
Classifier: Programming Language :: Python :: 3.10
Classifier: Programming Language :: Python :: 3.11
Classifier: Topic :: Software Development :: Testing
Classifier: Topic :: Internet :: WWW/HTTP
Requires-Python: >=3.8
License-File: LICENSE
Requires-Dist: requests>=2.28.0
Requires-Dist: jsonpath-ng>=1.5.3
Requires-Dist: pyyaml>=6.0
Requires-Dist: jsonschema>=4.17.0
Requires-Dist: faker>=18.0.0
Requires-Dist: pytest>=7.0.0
Requires-Dist: behave>=1.2.6
Requires-Dist: jinja2>=3.1.0
Requires-Dist: websocket-client>=1.5.0
Requires-Dist: beautifulsoup4>=4.12.0
Requires-Dist: python-dotenv>=1.0.0
Requires-Dist: PyJWT>=2.6.0
Provides-Extra: dev
Requires-Dist: pytest-cov>=4.0.0; extra == "dev"
Requires-Dist: black>=23.0.0; extra == "dev"
Requires-Dist: flake8>=6.0.0; extra == "dev"
Requires-Dist: mypy>=1.0.0; extra == "dev"
Provides-Extra: crypto
Requires-Dist: cryptography>=40.0.0; extra == "crypto"
Provides-Extra: xml
Requires-Dist: lxml>=4.9.0; extra == "xml"
Provides-Extra: excel
Requires-Dist: openpyxl>=3.0.0; extra == "excel"
Provides-Extra: websocket
Requires-Dist: websockets>=10.0; extra == "websocket"
Provides-Extra: graphql
Requires-Dist: graphql-core>=3.2.0; extra == "graphql"
Provides-Extra: full
Requires-Dist: cryptography>=40.0.0; extra == "full"
Requires-Dist: lxml>=4.9.0; extra == "full"
Requires-Dist: openpyxl>=3.0.0; extra == "full"
Requires-Dist: websockets>=10.0; extra == "full"
Requires-Dist: graphql-core>=3.2.0; extra == "full"
Dynamic: author
Dynamic: home-page
Dynamic: license-file
Dynamic: requires-python
